{
    "key": "group_67404d097c59a",
    "title": "Posts - Options",
    "fields": [
        {
            "key": "field_67404d08cce1b",
            "label": "Subtitle",
            "name": "subtitle",
            "aria-label": "",
            "type": "text",
            "instructions": "",
            "required": 0,
            "conditional_logic": 0,
            "wrapper": {
                "width": "",
                "class": "",
                "id": ""
            },
            "default_value": "",
            "maxlength": "",
            "allow_in_bindings": 0,
            "placeholder": "",
            "prepend": "",
            "append": ""
        },
        {
            "key": "field_67404d5ecce1c",
            "label": "Related Services",
            "name": "related_services",
            "aria-label": "",
            "type": "relationship",
            "instructions": "",
            "required": 0,
            "conditional_logic": 0,
            "wrapper": {
                "width": "",
                "class": "",
                "id": ""
            },
            "post_type": [
                "service"
            ],
            "post_status": "",
            "taxonomy": "",
            "filters": [
                "search"
            ],
            "return_format": "id",
            "min": "",
            "max": "",
            "allow_in_bindings": 0,
            "elements": "",
            "bidirectional": 0,
            "bidirectional_target": []
        }
    ],
    "location": [
        [
            {
                "param": "post_type",
                "operator": "==",
                "value": "post"
            }
        ],
        [
            {
                "param": "post_type",
                "operator": "==",
                "value": "case-study"
            }
        ]
    ],
    "menu_order": 2,
    "position": "normal",
    "style": "default",
    "label_placement": "top",
    "instruction_placement": "label",
    "hide_on_screen": "",
    "active": true,
    "description": "",
    "show_in_rest": 0,
    "modified": 1734628581
}
